{
    "UF": [
        {"id": "MG", "valor": "Minas Gerais", "chave": "MG"},      
        {"id": "RJ", "valor": "Rio de Janeiro", "chave": "RJ"},     
        {"id": "SP", "valor": "S達o Paulo", "chave": "SP"}
    ],
    "Cidades_SP": [      
        {"id": "Rio Claro", "valor":  "Rio Claro", "chave": "Rio Claro"},       
        {"id": "S達o Paulo", "valor":  "S達o Paulo", "chave": "S達o Paulo"}        
    ],
    "Cidades_RJ": [
        {"id": "Angra dos Reis", "valor": "Angra dos Reis", "chave": "Angra dos Reis"},       
        {"id": "Rio de Janeiro", "valor": "Rio de Janeiro", "chave": "Rio de Janeiro"}       
    ],
    "Bairros_RioClaro": [
        {"id": "1", "valor": "Bairo Rio Claro 1", "chave": "Bairo Rio Claro 1"},
        {"id": "2", "valor": "Bairo Rio Claro 2", "chave": "Bairo Rio Claro 2"},
    ],
    "Bairros_Angra": [
        {"id": "1", "valor": "Bairo Angra 1", "chave": "Bairo Angra 1"},
        {"id": "2", "valor": "Bairo Angra 2", "chave": "Bairo Angra 2"},
    ]
}
