{
    "UF": [
        {"id": "AC", "valor": "Acre", "chave": "AC"},
        {"id": "AL", "valor": "Alagoas", "chave": "AL"},
        {"id": "AP", "valor": "Amapá", "chave": "AP"},
        {"id": "AM", "valor": "Amazonas", "chave": "AM"},
        {"id": "BA", "valor": "Bahia", "chave": "BA"},
        {"id": "CE", "valor": "Ceará", "chave": "CE"},
        {"id": "DF", "valor": "Distrito Federal", "chave": "DF"},
        {"id": "ES", "valor": "Espírito Santo", "chave": "ES"},
        {"id": "GO", "valor": "Goiás", "chave": "GO"},
        {"id": "MA", "valor": "Maranhão", "chave": "MA"},
        {"id": "MT", "valor": "Mato Grosso", "chave": "MT"},
        {"id": "MS", "valor": "Mato Grosso do Sul", "chave": "MS"},
        {"id": "MG", "valor": "Minas Gerais", "chave": "MG"},
        {"id": "PA", "valor": "Pará", "chave": "PA"},
        {"id": "PB", "valor": "Paraíba", "chave": "PB"},
        {"id": "PR", "valor": "Paraná", "chave": "PR"},
        {"id": "PE", "valor": "Pernambuco", "chave": "PE"},
        {"id": "PI", "valor": "Piauí", "chave": "PI"},
        {"id": "RJ", "valor": "Rio de Janeiro", "chave": "RJ"},
        {"id": "RN", "valor": "Rio Grande do Norte", "chave": "RN"},
        {"id": "RS", "valor": "Rio Grande do Sul", "chave": "RS"},
        {"id": "RO", "valor": "Rondônia", "chave": "RO"},
        {"id": "RR", "valor": "Roraima", "chave": "RR"},
        {"id": "SC", "valor": "Santa Catarina", "chave": "SC"},
        {"id": "SP", "valor": "São Paulo", "chave": "SP"},
        {"id": "SE", "valor": "Sergipe", "chave": "SE"},
        {"id": "TO", "valor": "Tocantins", "chave": "TO"}
    ]
}
